hocmo/__init__.py
hocmo/hocmo.py
hocmo/utils.py
hocmo-1.0.1.dist-info/LICENSE.txt
hocmo-1.0.1.dist-info/METADATA
hocmo-1.0.1.dist-info/WHEEL
hocmo-1.0.1.dist-info/top_level.txt
hocmo-1.0.1.dist-info/RECORD
