Metadata-Version: 2.1
Name: hocmo
Version: 1.0.1
Summary: A Generalized Higher-Order Correlation Model (HOCMO) tool to generate scores modeling the strength of the relationship between triplicate entities using a tensor-based approach
Author: Charles Lu
Author-email: lucharles@wustl.edu
License: MIT
License-File: LICENSE.txt
Requires-Dist: pandas ==1.5.0
Requires-Dist: requests ==2.28.1
Requires-Dist: IPython ==8.5.0
Requires-Dist: ipykernel ==6.25.0
Requires-Dist: jupyter-client ==7.3.4
Requires-Dist: jupyter-core ==5.3.0
Requires-Dist: jupyterlab ==3.4.8
Requires-Dist: notebook ==6.4.12
Requires-Dist: matplotlib
Requires-Dist: setuptools
Requires-Dist: wheel
Requires-Dist: tensorly
Requires-Dist: rpy2
Requires-Dist: statistics
Requires-Dist: scikit-learn
Requires-Dist: scikit-tensor-py3
Requires-Dist: ncp
Requires-Dist: openpyxl
